MCP_Server/__init__.py
MCP_Server/server.py
ableton_mcp_extended-2.2.0.dist-info/licenses/LICENSE
ableton_mcp_extended-2.2.0.dist-info/METADATA
ableton_mcp_extended-2.2.0.dist-info/WHEEL
ableton_mcp_extended-2.2.0.dist-info/entry_points.txt
ableton_mcp_extended-2.2.0.dist-info/top_level.txt
ableton_mcp_extended-2.2.0.dist-info/RECORD
