Metadata-Version: 2.4
Name: ableton-mcp-extended
Version: 2.2.0
Summary: Extended Ableton Live integration with 76 tools through the Model Context Protocol
Author-email: IMNMV <nyk@example.com>
License: MIT
Project-URL: Homepage, https://github.com/IMNMV/ableton-mcp
Project-URL: Bug Tracker, https://github.com/IMNMV/ableton-mcp/issues
Classifier: Programming Language :: Python :: 3
Classifier: License :: OSI Approved :: MIT License
Classifier: Operating System :: OS Independent
Requires-Python: >=3.10
License-File: LICENSE
Requires-Dist: mcp[cli]>=1.3.0
Requires-Dist: audio2llm>=0.1.0
Dynamic: license-file
